roboslack/Dispatcher.py
roboslack/Exceptions.py
roboslack/MessageTypes.py
roboslack/__init__.py
roboslack/version.py
roboslack-0.1.3.dist-info/DESCRIPTION.rst
roboslack-0.1.3.dist-info/METADATA
roboslack-0.1.3.dist-info/RECORD
roboslack-0.1.3.dist-info/WHEEL
roboslack-0.1.3.dist-info/metadata.json
roboslack-0.1.3.dist-info/top_level.txt
