Metadata-Version: 2.0
Name: roboslack
Version: 0.1.3
Summary: Simple bot Framework using RTM Websocket API
Home-page: http://github.com/marclop/roboslack
Author: Marc Lopez
Author-email: marc5.12@outlook.com
License: UNKNOWN
Keywords: slack bot slackbot robot
Platform: UNKNOWN
Classifier: Intended Audience :: Developers
Classifier: License :: OSI Approved :: MIT License 
Classifier: Natural Language :: English
Classifier: Programming Language :: Python
Classifier: Programming Language :: Python :: 3
Classifier: Development Status :: 3 - Alpha
Requires-Dist: requests (==2.11.1)
Requires-Dist: slacksocket (==0.7)
